ouroboros/__init__.py
ouroboros/core.py
ouroboros/utils.py
ouroboros_arcpy-1.0.0b2.dist-info/licenses/LICENSE
ouroboros_arcpy-1.0.0b2.dist-info/METADATA
ouroboros_arcpy-1.0.0b2.dist-info/WHEEL
ouroboros_arcpy-1.0.0b2.dist-info/top_level.txt
ouroboros_arcpy-1.0.0b2.dist-info/RECORD
