Metadata-Version: 2.4
Name: ouroboros-arcpy
Version: 1.0.0b2
Summary: Wrapper class for pythonic use of arcpy Feature Classes
Author-email: Corbel <dev@corbelspatial.com>
License-Expression: MIT
Project-URL: homepage, https://pypi.org/project/ouroboros-arcpy/
Project-URL: documentation, https://app.readthedocs.org/projects/ouroboros-arcpy/
Project-URL: repository, https://github.com/corbel-spatial/ouroboros
Project-URL: issues, https://github.com/corbel-spatial/ouroboros/issues
Project-URL: changelog, https://github.com/corbel-spatial/ouroboros/blob/main/CHANGELOG.md
Classifier: Development Status :: 4 - Beta
Classifier: Programming Language :: Python :: 3.11
Classifier: Operating System :: Microsoft :: Windows :: Windows 11
Requires-Python: ==3.11.*
License-File: LICENSE
Requires-Dist: geojson
Requires-Dist: shapely
Dynamic: license-file
